tibl_cli/__init__.py
tibl_cli/__version__.py
tibl_cli/exc.py
tibl_cli/tibl.py
tibl_cli/ui.py
tibl_cli-0.0.2.dist-info/entry_points.txt
tibl_cli-0.0.2.dist-info/LICENSE
tibl_cli-0.0.2.dist-info/WHEEL
tibl_cli-0.0.2.dist-info/METADATA
tibl_cli-0.0.2.dist-info/RECORD
